specnn4pde/__init__.py
specnn4pde/colormaps.mat
specnn4pde/linalg.py
specnn4pde/myplot.py
specnn4pde/nn.py
specnn4pde/npde.py
specnn4pde/optim.py
specnn4pde/spectral.py
specnn4pde/torch_linalg.py
specnn4pde/torch_special.py
specnn4pde/utils.py
specnn4pde-0.2.5.dist-info/licenses/LICENSE
specnn4pde-0.2.5.dist-info/METADATA
specnn4pde-0.2.5.dist-info/WHEEL
specnn4pde-0.2.5.dist-info/top_level.txt
specnn4pde-0.2.5.dist-info/RECORD
